sketch_dask_extension-0.1.0.dist-info/LICENSE
sketch_dask_extension-0.1.0.dist-info/METADATA
sketch_dask_extension-0.1.0.dist-info/RECORD
sketch_dask_extension-0.1.0.dist-info/WHEEL
sketch_dask_extension-0.1.0.dist-info/top_level.txt
sketch_dask_extension/__init__.pyc
sketch_dask_extension/__version__.py
sketch_dask_extension/dask_extension.pyc
