Metadata-Version: 2.1
Name: sketch-dask-extension
Version: 0.1.0
Summary: Extension to support Dask Dataframes on Sketch
Author-email: YData <opensource@ydata.ai>
License: MIT License
Project-URL: Home, https://github.com/ydataai/sketch-dask-extension
Keywords: data,sketch,model,etl,automatic,join,ai,embedding,profiling,dask,dataframe
Classifier: License :: OSI Approved :: MIT License
Classifier: Development Status :: 5 - Production/Stable
Classifier: Intended Audience :: Developers
Classifier: Intended Audience :: Education
Classifier: Intended Audience :: End Users/Desktop
Classifier: Intended Audience :: Financial and Insurance Industry
Classifier: Intended Audience :: Healthcare Industry
Classifier: Intended Audience :: Science/Research
Classifier: Intended Audience :: Telecommunications Industry
Classifier: Operating System :: POSIX :: Linux
Classifier: Operating System :: MacOS
Classifier: Operating System :: Microsoft :: Windows
Classifier: Programming Language :: Python :: 3 :: Only
Classifier: Programming Language :: Python :: Implementation
Classifier: Topic :: Scientific/Engineering :: Artificial Intelligence
Classifier: Topic :: Software Development
Classifier: Topic :: Software Development :: Libraries :: Python Modules
Requires-Python: >=3.8
License-File: LICENSE
Requires-Dist: dask (>=2023.5.0)
Requires-Dist: sketch (>=0.4.2)
Provides-Extra: dev
Requires-Dist: pylint (==2.15.10) ; extra == 'dev'
Requires-Dist: black (==22.8.0) ; extra == 'dev'
Requires-Dist: flake8 (==6.0.0) ; extra == 'dev'
Requires-Dist: isort (==5.11.3) ; extra == 'dev'
Requires-Dist: pre-commit (==2.20.0) ; extra == 'dev'
Provides-Extra: packaging
Requires-Dist: twine ; extra == 'packaging'
Requires-Dist: build ; extra == 'packaging'
Requires-Dist: pyc-wheel ; extra == 'packaging'
Requires-Dist: mypy ; extra == 'packaging'
